LICENSE
README.md
setup.cfg
setup.py
gogov/__init__.py
gogov/topicinfo.py
gogov.egg-info/PKG-INFO
gogov.egg-info/SOURCES.txt
gogov.egg-info/dependency_links.txt
gogov.egg-info/entry_points.txt
gogov.egg-info/requires.txt
gogov.egg-info/top_level.txt