Metadata-Version: 2.4
Name: gogov
Version: 0.8.4
Summary: Unofficial API Client for GoGov CRM
Home-page: https://github.com/officeofperformancemanagement/gogov
Download-URL: https://github.com/officeofperformancemanagement/gogov/tarball/download
Author: Daniel J. Dufour
Author-email: daniel.j.dufour@gmail.com
Keywords: crm,data,gogov,python
Classifier: Development Status :: 4 - Beta
Classifier: Programming Language :: Python :: 3
Classifier: License :: CC0 1.0 Universal (CC0 1.0) Public Domain Dedication
Classifier: Operating System :: OS Independent
License-File: LICENSE
Requires-Dist: flatmate
Requires-Dist: requests
Dynamic: author
Dynamic: author-email
Dynamic: classifier
Dynamic: description
Dynamic: description-content-type
Dynamic: download-url
Dynamic: home-page
Dynamic: keywords
Dynamic: license-file
Dynamic: requires-dist
Dynamic: summary
